[{"displayTitle":"Abbaye du Mont des Cats","title":"abbayedumontdescats","image":"https://cheese.com/media/img/cheese/Mont_des_Cats_kaas.jpg","url":"https://cheese.com/abbaye-du-mont-des-cats/"},{"displayTitle":"Abbaye de Tamié","title":"abbayedetamié","image":"https://cheese.com/media/img/cheese/Abbaye_ND_de_Tamie.jpg","url":"https://cheese.com/tamie/"},{"displayTitle":"Abbaye de Belloc","title":"abbayedebelloc","image":"https://cheese.com/media/img/cheese/Abbaye-de-Belloc.jpg","url":"https://cheese.com/abbaye-de-belloc/"},{"displayTitle":"Adelost","title":"adelost","image":"https://cheese.com/media/img/cheese/Adelost_QnxYLx6.jpg","url":"https://cheese.com/adelost/"},{"displayTitle":"Abondance","title":"abondance","image":"https://cheese.com/media/img/cheese/Abondance1.jpg","url":"https://cheese.com/abondance/"},{"displayTitle":"Ackawi","title":"ackawi","image":"https://cheese.com/media/img/cheese/450px-Akawi_Cheese.jpg","url":"https://cheese.com/ackawi/"},{"displayTitle":"Abbaye de Citeaux","title":"abbayedeciteaux","image":"https://cheese.com/media/img/cheese/Abbaye-de-citeaux.jpg","url":"https://cheese.com/abbaye-de-citeaux/"},{"displayTitle":"Aisy Cendre","title":"aisycendre","image":"https://cheese.com/media/img/cheese/Aisy_cendre.jpg","url":"https://cheese.com/aisy-cendre/"},{"displayTitle":"Abbaye de Timadeuc","title":"abbayedetimadeuc","image":"https://cheese.com/media/img/cheese/687-abbaye_de_timadeuc.jpg","url":"https://cheese.com/abbaye-de-timadeuc/"},{"displayTitle":"Afuega'l Pitu","title":"afuegalpitu","image":"https://cheese.com/media/img/cheese/Afuega_l_pitu.jpeg","url":"https://cheese.com/afuegal-pitu/"},{"displayTitle":"Aged Gouda","title":"agedgouda","image":"https://cheese.com/media/img/cheese/Aged_Gouda_cheese_1.jpg","url":"https://cheese.com/aged-gouda/"},{"displayTitle":"Aged British Cheddar","title":"agedbritishcheddar","image":"https://cheese.com/media/img/cheese/27-aged-british-cheddar-shutterstock_1125720782.jpg","url":"https://cheese.com/aged-british-cheddar/"},{"displayTitle":"Airag","title":"airag","image":"https://cheese.com/media/img/cheese/Airag_2.JPG","url":"https://cheese.com/airag/"},{"displayTitle":"Amul Processed Cheese","title":"amulprocessedcheese","image":"https://cheese.com/media/img/cheese/Amul-Processed-Cheese.jpg","url":"https://cheese.com/amul-processed-cheese/"},{"displayTitle":"Appenzeller","title":"appenzeller","image":"https://cheese.com/media/img/cheese/Appenzeller.jpg","url":"https://cheese.com/appenzeller/"},{"displayTitle":"Ambert","title":"ambert","image":"https://cheese.com/media/img/cheese/Ambert.jpg","url":"https://cheese.com/ambert/"},{"displayTitle":"Amarelo de Beira Baixa","title":"amarelodebeirabaixa","image":"https://cheese.com/media/img/cheese/Amarelo_de_Beira_Baixa_sfMBsRQ.jpg","url":"https://cheese.com/amarelo-de-beira-baixa/"},{"displayTitle":"American Cheese","title":"americancheese","image":"https://cheese.com/media/img/cheese/10-American-Cheese-shutterstock_1610208106.jpg","url":"https://cheese.com/american-cheese/"},{"displayTitle":"Amul Cheese Spread","title":"amulcheesespread","image":"https://cheese.com/media/img/cheese/Amul-Cheese-Spread.jpg","url":"https://cheese.com/amul-cheese-spread/"},{"displayTitle":"Anejo Enchilado","title":"anejoenchilado","image":"https://cheese.com/media/img/cheese/Anejo_Enchilado.JPG","url":"https://cheese.com/anejo-enchilado/"},{"displayTitle":"Aura","title":"aura","image":"https://cheese.com/media/img/cheese/Aura_Cheese.jpg","url":"https://cheese.com/aura/"},{"displayTitle":"Aragon","title":"aragon","image":"https://cheese.com/media/img/cheese/16-ARAGON-shutterstock_86220250.jpg","url":"https://cheese.com/aragon/"},{"displayTitle":"Ami du Chambertin","title":"amiduchambertin","image":"https://cheese.com/media/img/cheese/Ami_du_Chambertin.jpg","url":"https://cheese.com/ami-du-chambertin/"},{"displayTitle":"Ashley","title":"ashley","image":"https://cheese.com/media/img/cheese/Ashley.jpg","url":"https://cheese.com/ashley/"},{"displayTitle":"Anari","title":"anari","image":"https://cheese.com/media/img/cheese/Anari_Cheese.jpg","url":"https://cheese.com/anari/"},{"displayTitle":"Anthotyro","title":"anthotyro","image":"https://cheese.com/media/img/cheese/Anthotyro.jpg","url":"https://cheese.com/anthotyro/"},{"displayTitle":"Babybel","title":"babybel","image":"https://cheese.com/media/img/cheese/Babybel.jpg","url":"https://cheese.com/babybel/"},{"displayTitle":"Baby Brie","title":"babybrie","image":"https://cheese.com/media/img/cheese/mini_brie.webp","url":"https://cheese.com/baby-brie/"},{"displayTitle":"Ardrahan","title":"ardrahan","image":"https://cheese.com/media/img/cheese/Ardrahan-Cheese.jpg","url":"https://cheese.com/ardrahan/"},{"displayTitle":"Bandal","title":"bandal","image":"https://cheese.com/media/img/cheese/Bandel_Cheese.jpg","url":"https://cheese.com/bandal/"},{"displayTitle":"Asiago DOP","title":"asiagodop","image":"https://cheese.com/media/img/cheese/asiago_it.jpg","url":"https://cheese.com/asiago/"},{"displayTitle":"Asiago d’Allevo DOP","title":"asiagod’allevodop","image":"https://cheese.com/media/img/cheese/Asiago_d_Allevo_DOP.jpg","url":"https://cheese.com/asiago-dallevo/"},{"displayTitle":"Armenian String Cheese","title":"armenianstringcheese","image":"https://cheese.com/media/img/cheese/03-armenian-string-cheese-shutterstock_1447310846.jpg","url":"https://cheese.com/armenian-string-cheese/"},{"displayTitle":"Banon","title":"banon","image":"https://cheese.com/media/img/cheese/banon3a_1.jpg","url":"https://cheese.com/banon/"},{"displayTitle":"Asiago Pressato DOP","title":"asiagopressatodop","image":"https://cheese.com/media/img/cheese/Asiago-Fresh.jpg","url":"https://cheese.com/asiago-pressato/"},{"displayTitle":"Baron Bigod","title":"baronbigod","image":"https://cheese.com/media/img/cheese/Baron-Bigod.jpg","url":"https://cheese.com/baron-bigod/"},{"displayTitle":"Azeitao","title":"azeitao","image":"https://cheese.com/media/img/cheese/Queijo_de_Azeitao.jpg","url":"https://cheese.com/azeitao/"},{"displayTitle":"Basajo","title":"basajo","image":"https://cheese.com/media/img/cheese/33-basajo-shutterstock_1292932108.jpg","url":"https://cheese.com/basajo/"},{"displayTitle":"Bavaria blu","title":"bavariablu","image":"https://cheese.com/media/img/cheese/Bavaria_blu.jpg","url":"https://cheese.com/bavaria-blu/"},{"displayTitle":"Baladi","title":"baladi","image":"https://cheese.com/media/img/cheese/baladi_2.jpg","url":"https://cheese.com/baladi/"},{"displayTitle":"Ardi Gasna","title":"ardigasna","image":"https://cheese.com/media/img/cheese/ardi-gasna.jpg","url":"https://cheese.com/ardi-gasna/"},{"displayTitle":"Basket Cheese","title":"basketcheese","image":"https://cheese.com/media/img/cheese/04-basket-cheese-shutterstock_372489670.jpg","url":"https://cheese.com/basket-cheese/"},{"displayTitle":"Baby Swiss","title":"babyswiss","image":"https://cheese.com/media/img/cheese/1100-baby_swiss.jpg","url":"https://cheese.com/baby-swiss/"},{"displayTitle":"Carre de l'Est","title":"carredelest","image":"https://cheese.com/media/img/cheese/wiki/carre-de-l'est.jpg","url":"https://cheese.com/carre-de-lest/"},{"displayTitle":"Chevre","title":"chevre","image":"https://cheese.com/media/img/cheese/Goats_cheese.jpg","url":"https://cheese.com/chevre/"},{"displayTitle":"Creamy Lancashire","title":"creamylancashire","image":"https://cheese.com/media/img/cheese/Lancashire_cheese.jpg","url":"https://cheese.com/creamy-lancashire/"},{"displayTitle":"Fontina","title":"fontina","image":"https://cheese.com/media/img/cheese/25-fontina-shutterstock_20880790.jpg","url":"https://cheese.com/fontina/"},{"displayTitle":"Fromage Corse","title":"fromagecorse","image":"https://cheese.com/media/img/cheese/Fromage-Corse.jpg","url":"https://cheese.com/fromage-corse/"},{"displayTitle":"Emmental","title":"emmental","image":"https://cheese.com/media/img/cheese/wiki/emmental.jpg","url":"https://cheese.com/emmental/"},{"displayTitle":"Epoisses de Bourgogne","title":"epoissesdebourgogne","image":"https://cheese.com/media/img/cheese/Epoisses_Bourgogne.jpg","url":"https://cheese.com/epoisses-de-bourgogne/"},{"displayTitle":"Leerdammer","title":"leerdammer","image":"https://cheese.com/media/img/cheese/Leerdammer_kaas.jpg","url":"https://cheese.com/leerdammer/"},{"displayTitle":"Cashel Blue","title":"cashelblue","image":"https://cheese.com/media/img/cheese/550-cashel_blue.jpg","url":"https://cheese.com/cashel-blue/"},{"displayTitle":"Idiazábal","title":"idiazábal","image":"https://cheese.com/media/img/cheese/Idiazabal2_Kv9htrq.jpg","url":"https://cheese.com/idiazabal/"},{"displayTitle":"Formaggio di capra","title":"formaggiodicapra","image":"https://cheese.com/media/img/cheese/Formaggio-di-capra.jpg","url":"https://cheese.com/formaggio-di-capra/"},{"displayTitle":"Fromage Blanc","title":"fromageblanc","image":"https://cheese.com/media/img/cheese/1356-fromage_blanc.jpg","url":"https://cheese.com/fromage-blanc/"},{"displayTitle":"Castelmagno","title":"castelmagno","image":"https://cheese.com/media/img/cheese/Castelmagno.jpg","url":"https://cheese.com/castelmagno/"},{"displayTitle":"Gorgonzola Dolce DOP","title":"gorgonzoladolcedop","image":"https://cheese.com/media/img/cheese/Gorgonzola_Dolce_DOP.jpg","url":"https://cheese.com/gorgonzola-dolce-dop/"},{"displayTitle":"Emental Grand Cru","title":"ementalgrandcru","image":"https://cheese.com/media/img/cheese/1_12.JPG","url":"https://cheese.com/emental-grand-cru/"},{"displayTitle":"Chaource","title":"chaource","image":"https://cheese.com/media/img/cheese/545-chaource.jpg","url":"https://cheese.com/chaource/"},{"displayTitle":"Crottin de Chavignol","title":"crottindechavignol","image":"https://cheese.com/media/img/cheese/Crottin_de_Chavignol_95dKGld.jpg","url":"https://cheese.com/crottin-du-chavignol/"},{"displayTitle":"Five Counties","title":"fivecounties","image":"https://cheese.com/media/img/cheese/11-five-counties-shutterstock_88701973.jpg","url":"https://cheese.com/five-counties/"},{"displayTitle":"Cropwell Bishop Blue Stilton","title":"cropwellbishopbluestilton","image":"https://cheese.com/media/img/cheese/920_cropwell_bishop_blue_stilton.jpg","url":"https://cheese.com/cropwell-bishop-blue-stilton/"},{"displayTitle":"Processed Cheese","title":"processedcheese","image":"https://cheese.com/media/img/cheese/1_8.jpg","url":"https://cheese.com/pasteurized-processed/"},{"displayTitle":"Greve","title":"greve","image":"https://cheese.com/media/img/cheese/wiki/greve.jpg","url":"https://cheese.com/greve/"},{"displayTitle":"Grey Owl","title":"greyowl","image":"https://cheese.com/media/img/cheese/Grey_Owl.jpg","url":"https://cheese.com/grey-owl/"},{"displayTitle":"Glebe Brethan","title":"glebebrethan","image":"https://cheese.com/media/img/cheese/Glebe_Brethan.JPG","url":"https://cheese.com/glebe-brethan/"},{"displayTitle":"Goats' Milk Caciotta","title":"goatsmilkcaciotta","image":"https://cheese.com/media/img/cheese/44-goats-milk-caciotta-new-shutterstock_254107552.jpg","url":"https://cheese.com/goats-milk-caciotta/"},{"displayTitle":"Harbison","title":"harbison","image":"https://cheese.com/media/img/cheese/1156-harbison.jpg","url":"https://cheese.com/harbison/"},{"displayTitle":"Goat ricotta","title":"goatricotta","image":"https://cheese.com/media/img/cheese/Goat-Ricotta.jpg","url":"https://cheese.com/goat-ricotta/"},{"displayTitle":"Gloucester","title":"gloucester","image":"https://cheese.com/media/img/cheese/Gloucester-cheese.jpg","url":"https://cheese.com/gloucester/"},{"displayTitle":"Tommes","title":"tommes","image":"https://cheese.com/media/img/cheese/Tomme.jpg","url":"https://cheese.com/tommes/"},{"displayTitle":"Fleur du Maquis","title":"fleurdumaquis","image":"https://cheese.com/media/img/cheese/Fleur-du-Maquis.jpg","url":"https://cheese.com/fleur-du-maquis/"},{"displayTitle":"Fromage Frais","title":"fromagefrais","image":"https://cheese.com/media/img/cheese/14-FROMAGE-FRAIS-shutterstock_318526556.jpg","url":"https://cheese.com/fromage-frais/"},{"displayTitle":"Tymsboro","title":"tymsboro","image":"https://cheese.com/media/img/cheese/Tymsboro.JPG","url":"https://cheese.com/tymsboro/"},{"displayTitle":"Frying Cheese","title":"fryingcheese","image":"https://cheese.com/media/img/cheese/1_39.JPG","url":"https://cheese.com/frying-cheese/"},{"displayTitle":"Bayley Hazen Blue","title":"bayleyhazenblue","image":"https://cheese.com/media/img/cheese/1154-bayley_hazen_blue.jpg","url":"https://cheese.com/bayley-hazen-blue/"},{"displayTitle":"Swiss cheese","title":"swisscheese","image":"https://cheese.com/media/img/cheese/wiki/swiss.jpg","url":"https://cheese.com/swiss/"},{"displayTitle":"Flor de Guia","title":"flordeguia","image":"https://cheese.com/media/img/cheese/Queso_de_flor_1.jpg","url":"https://cheese.com/flor-de-guia/"},{"displayTitle":"Fromage de Montagne de Savoie","title":"fromagedemontagnedesavoie","image":"https://cheese.com/media/img/cheese/Fromage-de-Montagne-de-Savoie.jpg","url":"https://cheese.com/fromage-de-montagne-de-savoie/"},{"displayTitle":"Camembert de Normandie","title":"camembertdenormandie","image":"https://cheese.com/media/img/cheese/Camembert_normandie.jpg","url":"https://cheese.com/camembert-de-normandie/"},{"displayTitle":"Camembert","title":"camembert","image":"https://cheese.com/media/img/cheese/Camembert.jpg","url":"https://cheese.com/camembert/"},{"displayTitle":"Graddost","title":"graddost","image":"https://cheese.com/media/img/cheese/graddost.jpg","url":"https://cheese.com/graddost/"},{"displayTitle":"Boulette d'Avesnes","title":"boulettedavesnes","image":"https://cheese.com/media/img/cheese/Boulette_dAvesnes.jpg","url":"https://cheese.com/boulette-davesnes/"},{"displayTitle":"Fourme de Montbrison","title":"fourmedemontbrison","image":"https://cheese.com/media/img/cheese/Fourme_montbrison.jpg","url":"https://cheese.com/fourme-de-montbrison/"},{"displayTitle":"Charolais","title":"charolais","image":"https://cheese.com/media/img/cheese/Charolais.jpg","url":"https://cheese.com/charolais/"},{"displayTitle":"Crottin de Chavignol","title":"crottindechavignol","image":"https://cheese.com/media/img/cheese/Crottin_de_Chavignol.jpg","url":"https://cheese.com/crottin-de-chavignol/"},{"displayTitle":"Chaumes","title":"chaumes","image":"https://cheese.com/media/img/cheese/Chaumes.jpg","url":"https://cheese.com/chaumes/"},{"displayTitle":"Cure Nantais","title":"curenantais","image":"https://cheese.com/media/img/cheese/1_21.JPG","url":"https://cheese.com/cure-nantais/"},{"displayTitle":"Chavroux","title":"chavroux","image":"https://cheese.com/media/img/cheese/Chavroux.jpg","url":"https://cheese.com/chavroux/"},{"displayTitle":"Gorgonzola Cremificato","title":"gorgonzolacremificato","image":"https://cheese.com/media/img/cheese/1_13.JPG","url":"https://cheese.com/gorgonzola-cremificato/"},{"displayTitle":"Gorgonzola","title":"gorgonzola","image":"https://cheese.com/media/img/cheese/Gorgonzola_niUHULx.jpg","url":"https://cheese.com/gorgonzola/"},{"displayTitle":"Reggianito","title":"reggianito","image":"https://cheese.com/media/img/cheese/Reggianito.jpg","url":"https://cheese.com/reggianito/"},{"displayTitle":"Cambozola Grand Noir","title":"cambozolagrandnoir","image":"https://cheese.com/media/img/cheese/Cambozola_Grand_Noir.jpg","url":"https://cheese.com/cambozola-grand-noir/"},{"displayTitle":"Scamorza","title":"scamorza","image":"https://cheese.com/media/img/cheese/Scamorza_1.jpg","url":"https://cheese.com/scamorza/"},{"displayTitle":"Calenzana (Calinzanincu)","title":"calenzana(calinzanincu)","image":"https://cheese.com/media/img/cheese/1_3.jpg","url":"https://cheese.com/calenzana/"},{"displayTitle":"Cahill's Irish Porter Cheddar","title":"cahillsirishportercheddar","image":"https://cheese.com/media/img/cheese/05-cahills-irish-porter-cheddar-shutterstock_1563775300.jpg","url":"https://cheese.com/cahills-irish-porter-cheddar/"},{"displayTitle":"Caciotta","title":"caciotta","image":"https://cheese.com/media/img/cheese/22-Caciotta-shutterstock_632211605.jpg","url":"https://cheese.com/caciotta/"},{"displayTitle":"Caerphilly","title":"caerphilly","image":"https://cheese.com/media/img/cheese/1719-caerphilly.jpg","url":"https://cheese.com/caerphilly/"},{"displayTitle":"Caciotta Al Tartufo","title":"caciottaaltartufo","image":"https://cheese.com/media/img/cheese/Caciotta-al-Tartufo.jpg","url":"https://cheese.com/caciotta-al-tartufo/"},{"displayTitle":"Cacio De Roma®","title":"cacioderoma","image":"https://cheese.com/media/img/cheese/Cacio_de_Roma.jpg","url":"https://cheese.com/cacio-de-roma/"},{"displayTitle":"Caciocavallo di Bufala","title":"caciocavallodibufala","image":"https://cheese.com/media/img/cheese/Caciocavallo_di_Bufala_GswzFEK.jpg","url":"https://cheese.com/caciocavallo-di-bufala/"},{"displayTitle":"Caciocavallo","title":"caciocavallo","image":"https://cheese.com/media/img/cheese/Caciocavallo.jpg","url":"https://cheese.com/caciocavallo/"},{"displayTitle":"Crescenza","title":"crescenza","image":"https://cheese.com/media/img/cheese/Crescenza.jpg","url":"https://cheese.com/crescenza/"},{"displayTitle":"Caprice des Dieux","title":"capricedesdieux","image":"https://cheese.com/media/img/cheese/1819-caprice_des_dieux.jpg","url":"https://cheese.com/caprice-des-dieux/"},{"displayTitle":"Goya","title":"goya","image":"https://cheese.com/media/img/cheese/34-goya-shutterstock_1383826232.jpg","url":"https://cheese.com/goya/"},{"displayTitle":"Gorgonzola Piccante DOP","title":"gorgonzolapiccantedop","image":"https://cheese.com/media/img/cheese/Gorgonzola_Piccante_DOP.jpg","url":"https://cheese.com/gorgonzola-piccante-dop/"},{"displayTitle":"Castelo Branco","title":"castelobranco","image":"https://cheese.com/media/img/cheese/Queijo_de_Castelo_Branco.jpg","url":"https://cheese.com/castelo-branco/"},{"displayTitle":"Casatica","title":"casatica","image":"https://cheese.com/media/img/cheese/Casatica.jpg","url":"https://cheese.com/casatica/"},{"displayTitle":"Gorwydd Caerphilly","title":"gorwyddcaerphilly","image":"https://cheese.com/media/img/cheese/Gorwydd-Caerphilly.jpg","url":"https://cheese.com/gorwydd-caerphilly/"},{"displayTitle":"Fresh Chevre","title":"freshchevre","image":"https://cheese.com/media/img/cheese/1578-fresh_chevre.jpg","url":"https://cheese.com/fresh-chevre/"},{"displayTitle":"Kefalotyri","title":"kefalotyri","image":"https://cheese.com/media/img/cheese/Kefalotyri.jpg","url":"https://cheese.com/kefalotyri/"},{"displayTitle":"Geitost","title":"geitost","image":"https://cheese.com/media/img/cheese/Geitost.jpg","url":"https://cheese.com/geitost/"},{"displayTitle":"Garrotxa","title":"garrotxa","image":"https://cheese.com/media/img/cheese/Garrotxa.jpg","url":"https://cheese.com/garrotxa/"},{"displayTitle":"La Peral","title":"laperal","image":"https://cheese.com/media/img/cheese/1455-la_peral.jpg","url":"https://cheese.com/la-peral/"},{"displayTitle":"Lacy Swiss","title":"lacyswiss","image":"https://cheese.com/media/img/cheese/23-Lacy-Swiss--shutterstock_1086462719.jpg","url":"https://cheese.com/lacy-swiss/"},{"displayTitle":"President Camembert","title":"presidentcamembert","image":"https://cheese.com/media/img/cheese/President_Camembert.jpg","url":"https://cheese.com/president-camembert/"},{"displayTitle":"Cheddar with Irish Porter","title":"cheddarwithirishporter","image":"https://cheese.com/media/img/cheese/610-cheddar_with_irish_porter.jpg","url":"https://cheese.com/cheddar-with-irish-porter/"},{"displayTitle":"Beaufort","title":"beaufort","image":"https://cheese.com/media/img/cheese/24-beaufort-shutterstock_447054049.jpg","url":"https://cheese.com/beaufort/"},{"displayTitle":"Cheddar","title":"cheddar","image":"https://cheese.com/media/img/cheese/wiki/cheddar.jpg","url":"https://cheese.com/cheddar/"},{"displayTitle":"Farm Chanco","title":"farmchanco","image":"https://cheese.com/media/img/cheese/Quesochancojpeg.jpg","url":"https://cheese.com/farm-chanco/"},{"displayTitle":"Cheese Curds","title":"cheesecurds","image":"https://cheese.com/media/img/cheese/Cheese-Curds.jpg","url":"https://cheese.com/cheese-curds/"},{"displayTitle":"Farmer cheese","title":"farmercheese","image":"https://cheese.com/media/img/cheese/Farmer_Cheese_.jpg","url":"https://cheese.com/farmer/"},{"displayTitle":"Gamonéu","title":"gamonéu","image":"https://cheese.com/media/img/cheese/Gamonedo.JPG","url":"https://cheese.com/gamoneu/"},{"displayTitle":"Gammelost","title":"gammelost","image":"https://cheese.com/media/img/cheese/644-gammelost.jpg","url":"https://cheese.com/gammelost/"},{"displayTitle":"Blue Castello","title":"bluecastello","image":"https://cheese.com/media/img/cheese/CastelloBlueCheese.jpg","url":"https://cheese.com/blue-castello/"},{"displayTitle":"Bleu Bénédictin","title":"bleubénédictin","image":"https://cheese.com/media/img/cheese/689-bleu_benedictin.jpg","url":"https://cheese.com/bleu-benedictin/"},{"displayTitle":"Galbani","title":"galbani","image":"https://cheese.com/media/img/cheese/Galbani.jpg","url":"https://cheese.com/galbani/"},{"displayTitle":"Bocconcini","title":"bocconcini","image":"https://cheese.com/media/img/cheese/Bocconcini_gobeirne_V0API9t.jpg","url":"https://cheese.com/bocconcini/"},{"displayTitle":"Bleu Des Causses","title":"bleudescausses","image":"https://cheese.com/media/img/cheese/Bleu_des_Causses.JPG","url":"https://cheese.com/bleu-des-causses/"},{"displayTitle":"Blythedale Camembert","title":"blythedalecamembert","image":"https://cheese.com/media/img/cheese/782-blythedale_camembert.jpg","url":"https://cheese.com/blythedale-camembert/"},{"displayTitle":"Berkswell","title":"berkswell","image":"https://cheese.com/media/img/cheese/543-berkswell.jpg","url":"https://cheese.com/berkswell/"},{"displayTitle":"Bleu d'Auvergne","title":"bleudauvergne","image":"https://cheese.com/media/img/cheese/Bleu_auvergne.jpg","url":"https://cheese.com/bleu-dauvergne/"},{"displayTitle":"Blue Vein Cheese","title":"blueveincheese","image":"https://cheese.com/media/img/cheese/blue.jpg","url":"https://cheese.com/blue-vein-cheese/"},{"displayTitle":"Blue Vein (Australian)","title":"bluevein(australian)","image":"https://cheese.com/media/img/cheese/Roaring_Forties_Blue_Cheese.jpg","url":"https://cheese.com/blue-vein-australian/"},{"displayTitle":"Boeren-Leidse met sleutels","title":"boeren-leidsemetsleutels","image":"https://cheese.com/media/img/cheese/Leyden_cheese.jpg","url":"https://cheese.com/boeren-leidse-met-sleutels/"},{"displayTitle":"Brânză de Burduf","title":"brânzădeburduf","image":"https://cheese.com/media/img/cheese/cheese_wrapped_in_fir_bark.jpg","url":"https://cheese.com/branza-de-burduf/"},{"displayTitle":"Briquette de Brebis","title":"briquettedebrebis","image":"https://cheese.com/media/img/cheese/1_19.JPG","url":"https://cheese.com/briquette-de-brebis/"},{"displayTitle":"Brie de Meaux","title":"briedemeaux","image":"https://cheese.com/media/img/cheese/Brie_de_Meaux_1.jpg","url":"https://cheese.com/brie-de-meaux/"},{"displayTitle":"Brousse du Rove","title":"broussedurove","image":"https://cheese.com/media/img/cheese/Brousse_du_Rove.jpg","url":"https://cheese.com/brousse-du-rove/"},{"displayTitle":"Buche de Chevre","title":"buchedechevre","image":"https://cheese.com/media/img/cheese/1815-buche_de_chevre.jpg","url":"https://cheese.com/buche-de-chevre/"},{"displayTitle":"Burgos","title":"burgos","image":"https://cheese.com/media/img/cheese/Queso_De_Burgos.JPG","url":"https://cheese.com/burgos/"},{"displayTitle":"Danbo","title":"danbo","image":"https://cheese.com/media/img/cheese/625-danbo.jpg","url":"https://cheese.com/danbo/"},{"displayTitle":"Danablu (Danish Blue)","title":"danablu(danishblue)","image":"https://cheese.com/media/img/cheese/Danablu-Danish-Blue.jpg","url":"https://cheese.com/danablu-danish-blue/"},{"displayTitle":"Danish Feta","title":"danishfeta","image":"https://cheese.com/media/img/cheese/1061-danish_feta.jpg","url":"https://cheese.com/danish-feta/"},{"displayTitle":"Crotonese","title":"crotonese","image":"https://cheese.com/media/img/cheese/Pecorino_Crotonese.jpg","url":"https://cheese.com/crotonese/"},{"displayTitle":"Danish Fontina","title":"danishfontina","image":"https://cheese.com/media/img/cheese/danish_fontina.jpg","url":"https://cheese.com/danish-fontina/"},{"displayTitle":"Cuajada","title":"cuajada","image":"https://cheese.com/media/img/cheese/Cuajada.jpg","url":"https://cheese.com/cuajada/"},{"displayTitle":"Gubbeen","title":"gubbeen","image":"https://cheese.com/media/img/cheese/GubbeenCheeseWeb.jpg","url":"https://cheese.com/gubbeen/"},{"displayTitle":"Chabichou du Poitou","title":"chabichoudupoitou","image":"https://cheese.com/media/img/cheese/chabichou.jpg","url":"https://cheese.com/chabichou-du-poitou/"},{"displayTitle":"Cendre d'Olivet","title":"cendredolivet","image":"https://cheese.com/media/img/cheese/Olivet_cendre_2.jpg","url":"https://cheese.com/cendre-dolivet/"},{"displayTitle":"Catupiry","title":"catupiry","image":"https://cheese.com/media/img/cheese/606-catupiry.jpg","url":"https://cheese.com/catupiry/"},{"displayTitle":"Caveman Blue","title":"cavemanblue","image":"https://cheese.com/media/img/cheese/544-caveman_blue.jpg","url":"https://cheese.com/caveman-blue/"},{"displayTitle":"Casu marzu","title":"casumarzu","image":"https://cheese.com/media/img/cheese/Casu_Marzu_cheese.jpg","url":"https://cheese.com/casu-marzu/"},{"displayTitle":"Cotija","title":"cotija","image":"https://cheese.com/media/img/cheese/08-cotija-shutterstock_171554048.jpg","url":"https://cheese.com/cotija/"},{"displayTitle":"Cana de Cabra","title":"canadecabra","image":"https://cheese.com/media/img/cheese/Cana-de-Cabra-Low.jpg","url":"https://cheese.com/cana-de-cabra/"},{"displayTitle":"Coulommiers","title":"coulommiers","image":"https://cheese.com/media/img/cheese/wiki/coulommiers.jpg","url":"https://cheese.com/coulommiers/"},{"displayTitle":"Canastra cheese","title":"canastracheese","image":"https://cheese.com/media/img/cheese/1822-canastra_cheese.jpg","url":"https://cheese.com/canastra-cheese/"},{"displayTitle":"Coalho","title":"coalho","image":"https://cheese.com/media/img/cheese/Queijo_coalho.jpg","url":"https://cheese.com/coalho/"},{"displayTitle":"Cougar Gold","title":"cougargold","image":"https://cheese.com/media/img/cheese/1763_cougar_gold.jpg","url":"https://cheese.com/cougar-gold/"},{"displayTitle":"Cabrales","title":"cabrales","image":"https://cheese.com/media/img/cheese/cabrales.jpg","url":"https://cheese.com/cabrales/"},{"displayTitle":"Caboc","title":"caboc","image":"https://cheese.com/media/img/cheese/26-caboc-shutterstock_1329224714.jpg","url":"https://cheese.com/caboc/"},{"displayTitle":"Cachaille","title":"cachaille","image":"https://cheese.com/media/img/cheese/1_20.JPG","url":"https://cheese.com/cachaille/"},{"displayTitle":"Cabecou","title":"cabecou","image":"https://cheese.com/media/img/cheese/Cabecou.jpg","url":"https://cheese.com/cabecou/"},{"displayTitle":"Colby-Jack","title":"colby-jack","image":"https://cheese.com/media/img/cheese/wiki/colby-jack.jpg","url":"https://cheese.com/colby-jack/"},{"displayTitle":"Colby","title":"colby","image":"https://cheese.com/media/img/cheese/wiki/colby.jpg","url":"https://cheese.com/colby/"},{"displayTitle":"Crema Mexicana Agria","title":"cremamexicanaagria","image":"https://cheese.com/media/img/cheese/crema-mexicana-agria.jpg","url":"https://cheese.com/crema-agria/"},{"displayTitle":"Cardo","title":"cardo","image":"https://cheese.com/media/img/cheese/Cardo.jpg","url":"https://cheese.com/cardo/"},{"displayTitle":"Fior Di Latte","title":"fiordilatte","image":"https://cheese.com/media/img/cheese/mozzarella.jpg","url":"https://cheese.com/fior-di-latte/"},{"displayTitle":"Fiscalini Bandaged Cheddar","title":"fiscalinibandagedcheddar","image":"https://cheese.com/media/img/cheese/1032-fiscalini_bandaged_cheddar.jpg","url":"https://cheese.com/fiscalini-bandaged-cheddar/"},{"displayTitle":"Cottage Cheese (Australian)","title":"cottagecheese(australian)","image":"https://cheese.com/media/img/cheese/Cottagecheese.jpg","url":"https://cheese.com/cottage-cheese-australian/"},{"displayTitle":"Cornish Yarg","title":"cornishyarg","image":"https://cheese.com/media/img/cheese/624-cornish_yarg.jpg","url":"https://cheese.com/cornish-yarg/"},{"displayTitle":"Cotherstone","title":"cotherstone","image":"https://cheese.com/media/img/cheese/cotherstone.jpg","url":"https://cheese.com/cotherstone/"},{"displayTitle":"Cottage Cheese","title":"cottagecheese","image":"https://cheese.com/media/img/cheese/514_cottage_cheese.jpg","url":"https://cheese.com/cottage-cheese/"},{"displayTitle":"Cotswold","title":"cotswold","image":"https://cheese.com/media/img/cheese/19-cotswold-shutterstock_55436554.jpg","url":"https://cheese.com/cotswold/"},{"displayTitle":"Coolea","title":"coolea","image":"https://cheese.com/media/img/cheese/595-coolea.jpg","url":"https://cheese.com/coolea/"},{"displayTitle":"Cornish Brie","title":"cornishbrie","image":"https://cheese.com/media/img/cheese/598-cornish_brie.jpg","url":"https://cheese.com/cornish-brie/"},{"displayTitle":"ColoRouge","title":"colorouge","image":"https://cheese.com/media/img/cheese/ColoRouge.jpg","url":"https://cheese.com/colorouge/"},{"displayTitle":"Condio","title":"condio","image":"https://cheese.com/media/img/cheese/Condio.jpg","url":"https://cheese.com/condio/"},{"displayTitle":"Comte","title":"comte","image":"https://cheese.com/media/img/cheese/600-comte.jpg","url":"https://cheese.com/comte/"},{"displayTitle":"Esrom","title":"esrom","image":"https://cheese.com/media/img/cheese/Esrom.jpg","url":"https://cheese.com/esrom/"},{"displayTitle":"Etorki","title":"etorki","image":"https://cheese.com/media/img/cheese/Fromage_Etorki.jpg","url":"https://cheese.com/etorki/"},{"displayTitle":"Edelpilz","title":"edelpilz","image":"https://cheese.com/media/img/cheese/Edelpilz.jpg","url":"https://cheese.com/edelpilz/"},{"displayTitle":"Dolcelatte","title":"dolcelatte","image":"https://cheese.com/media/img/cheese/532_dolcelatte.jpg","url":"https://cheese.com/dolcelatte/"},{"displayTitle":"Delice de Bourgogne","title":"delicedebourgogne","image":"https://cheese.com/media/img/cheese/1052-delice_de_bourgogne.jpg","url":"https://cheese.com/delice-de-bourgogne/"},{"displayTitle":"Colony cheese","title":"colonycheese","image":"https://cheese.com/media/img/cheese/Colony_cheese.jpg","url":"https://cheese.com/colony-cheese/"},{"displayTitle":"Edam","title":"edam","image":"https://cheese.com/media/img/cheese/EdamCheese.jpg","url":"https://cheese.com/edam/"},{"displayTitle":"Colston Bassett Stilton","title":"colstonbassettstilton","image":"https://cheese.com/media/img/cheese/Colston_Bassett_Stilton.JPG","url":"https://cheese.com/colston-bassett-stilton/"},{"displayTitle":"Durrus","title":"durrus","image":"https://cheese.com/media/img/cheese/38-durrus-shutterstock_375008764.jpg","url":"https://cheese.com/durrus/"},{"displayTitle":"Dunlop","title":"dunlop","image":"https://cheese.com/media/img/cheese/955-dunlop.jpg","url":"https://cheese.com/dunlop/"},{"displayTitle":"Dragons Breath Blue","title":"dragonsbreathblue","image":"https://cheese.com/media/img/cheese/Dragons_Breath.jpg","url":"https://cheese.com/dragons-breath-blue/"},{"displayTitle":"Dorset Blue Vinny","title":"dorsetbluevinny","image":"https://cheese.com/media/img/cheese/Dorset_Blue_Vinney_cheese.jpg","url":"https://cheese.com/dorset-blue-vinny/"},{"displayTitle":"Dry Jack","title":"dryjack","image":"https://cheese.com/media/img/cheese/427px-Sonoma_Dry_Jack.jpg","url":"https://cheese.com/dry-jack/"},{"displayTitle":"Dorblu","title":"dorblu","image":"https://cheese.com/media/img/cheese/1168-dorblu.jpg","url":"https://cheese.com/dorblu/"},{"displayTitle":"Dorstone","title":"dorstone","image":"https://cheese.com/media/img/cheese/dorstone.JPG","url":"https://cheese.com/dorstone/"},{"displayTitle":"Don Olivo","title":"donolivo","image":"https://cheese.com/media/img/cheese/1200-don_olivo.jpg","url":"https://cheese.com/don-olivo/"},{"displayTitle":"Derby","title":"derby","image":"https://cheese.com/media/img/cheese/Sage_derby_cheese_EekCJQe.jpg","url":"https://cheese.com/derby/"},{"displayTitle":"Barricato al Pepe","title":"barricatoalpepe","image":"https://cheese.com/media/img/cheese/Barricato_al_Pepe.jpg","url":"https://cheese.com/barricato-al-pepe/"},{"displayTitle":"Beyaz Peynir","title":"beyazpeynir","image":"https://cheese.com/media/img/cheese/Beyaz-Peynir.jpg","url":"https://cheese.com/beyaz-peynir/"},{"displayTitle":"Bavarian Bergkase","title":"bavarianbergkase","image":"https://cheese.com/media/img/cheese/Bavarian_Bergkase.jpg","url":"https://cheese.com/bavarian-bergkase/"},{"displayTitle":"Beemster Extra Aged (XO)","title":"beemsterextraaged(xo)","image":"https://cheese.com/media/img/cheese/757-beemster_extra_aged.jpg","url":"https://cheese.com/beemster-extra-aged/"},{"displayTitle":"Bel Paese","title":"belpaese","image":"https://cheese.com/media/img/cheese/604-bel_paese.jpg","url":"https://cheese.com/bel-paese/"},{"displayTitle":"Beemster Classic","title":"beemsterclassic","image":"https://cheese.com/media/img/cheese/30-beemster-classic-shutterstock_168147977.jpg","url":"https://cheese.com/beemster-classic/"},{"displayTitle":"Bierkase","title":"bierkase","image":"https://cheese.com/media/img/cheese/Bierkase.jpg","url":"https://cheese.com/bierkase/"},{"displayTitle":"Bethmale des Pyrenees","title":"bethmaledespyrenees","image":"https://cheese.com/media/img/cheese/Bethmale.jpg","url":"https://cheese.com/bethmale-des-pyrenees/"},{"displayTitle":"Blacksticks Blue","title":"blacksticksblue","image":"https://cheese.com/media/img/cheese/13-blacksticks-blue-shutterstock_108187130.jpg","url":"https://cheese.com/blacksticks-blue/"},{"displayTitle":"Butterkase","title":"butterkase","image":"https://cheese.com/media/img/cheese/DeutschButterkase.jpg","url":"https://cheese.com/butterkase/"},{"displayTitle":"Burrata","title":"burrata","image":"https://cheese.com/media/img/cheese/587-burrata.jpg","url":"https://cheese.com/burrata/"},{"displayTitle":"Feta","title":"feta","image":"https://cheese.com/media/img/cheese/504_feta.jpg","url":"https://cheese.com/feta/"},{"displayTitle":"Filetta","title":"filetta","image":"https://cheese.com/media/img/cheese/685-filetta.jpg","url":"https://cheese.com/filetta/"},{"displayTitle":"Cream Havarti","title":"creamhavarti","image":"https://cheese.com/media/img/cheese/Havarathi.jpg","url":"https://cheese.com/cream-havarti/"},{"displayTitle":"Fiore Sardo","title":"fioresardo","image":"https://cheese.com/media/img/cheese/Fiore_Sardo.jpg","url":"https://cheese.com/fiore-sardo/"},{"displayTitle":"Finn","title":"finn","image":"https://cheese.com/media/img/cheese/finn.jpg","url":"https://cheese.com/finn/"},{"displayTitle":"Chhurpi","title":"chhurpi","image":"https://cheese.com/media/img/cheese/800px-Chhurpi.jpg","url":"https://cheese.com/chhurpi/"},{"displayTitle":"Cheshire","title":"cheshire","image":"https://cheese.com/media/img/cheese/Cheshire_Cheese.jpg","url":"https://cheese.com/cheshire/"},{"displayTitle":"Cream Cheese","title":"creamcheese","image":"https://cheese.com/media/img/cheese/cream_cheese_bagel.jpg","url":"https://cheese.com/cream-cheese/"}]